Metadata-Version: 2.1
Name: py-prettylog
Version: 0.3
Summary: Pretty looking logging library that's also extremely functional.
Home-page: https://github.com/bossauh/prettylog
Download-URL: https://github.com/bossauh/prettylog/archive/refs/tags/v_03.tar.gz
Author: Philippe Mathew
Author-email: philmattdev@gmail.com
License: MIT
Keywords: logger,logging
Platform: UNKNOWN
Classifier: Development Status :: 4 - Beta
Classifier: Intended Audience :: Developers
Classifier: Topic :: Software Development :: Build Tools
Classifier: License :: OSI Approved :: MIT License
Classifier: Programming Language :: Python :: 3.6
Classifier: Programming Language :: Python :: 3.7
License-File: LICENSE
